myCalculatorPackageCraig/__init__.py
myCalculatorPackageCraig/division/__init__.py
myCalculatorPackageCraig/division/divide.py
myCalculatorPackageCraig/multiplication/__init__.py
myCalculatorPackageCraig/multiplication/multiply.py
myCalculatorPackageCraig-0.0.2.dist-info/LICENSE.txt
myCalculatorPackageCraig-0.0.2.dist-info/METADATA
myCalculatorPackageCraig-0.0.2.dist-info/WHEEL
myCalculatorPackageCraig-0.0.2.dist-info/top_level.txt
myCalculatorPackageCraig-0.0.2.dist-info/RECORD
